rumoca-0.7.28.dist-info/METADATA
rumoca-0.7.28.dist-info/WHEEL
rumoca/__init__.py
rumoca/_native.cp312-win_amd64.pyd
rumoca/compiler.py
rumoca/version.py
rumoca-0.7.28.dist-info/RECORD
