Metadata-Version: 2.4
Name: rumoca
Version: 0.7.28
Classifier: Development Status :: 3 - Alpha
Classifier: Intended Audience :: Science/Research
Classifier: License :: OSI Approved :: Apache Software License
Classifier: Programming Language :: Python :: 3
Classifier: Programming Language :: Python :: 3.8
Classifier: Programming Language :: Python :: 3.9
Classifier: Programming Language :: Python :: 3.10
Classifier: Programming Language :: Python :: 3.11
Classifier: Programming Language :: Python :: 3.12
Classifier: Programming Language :: Rust
Classifier: Topic :: Scientific/Engineering
Classifier: Topic :: Software Development :: Code Generators
Classifier: Topic :: Software Development :: Compilers
Requires-Dist: pytest>=7.0 ; extra == 'dev'
Requires-Dist: pytest-cov>=4.0 ; extra == 'dev'
Requires-Dist: black>=23.0 ; extra == 'dev'
Requires-Dist: mypy>=1.0 ; extra == 'dev'
Requires-Dist: cyecca ; extra == 'cyecca'
Provides-Extra: dev
Provides-Extra: cyecca
Summary: Python interface for the Rumoca Modelica compiler
Keywords: modelica,compiler,simulation,dae,code-generation
Home-Page: https://github.com/cognipilot/rumoca
Author: Rumoca Contributors
License: Apache-2.0
Requires-Python: >=3.8
Project-URL: Homepage, https://github.com/cognipilot/rumoca
Project-URL: Documentation, https://github.com/cognipilot/rumoca/blob/main/README.md
Project-URL: Repository, https://github.com/cognipilot/rumoca
Project-URL: Issues, https://github.com/cognipilot/rumoca/issues
